CHANGES.rst
MANIFEST.in
README.rst
setup.cfg
setup.py
sphinxcontrib/__init__.py
sphinxcontrib/osexample.css
sphinxcontrib/osexample.js
sphinxcontrib/osexample.py
sphinxcontrib_osexample.egg-info/PKG-INFO
sphinxcontrib_osexample.egg-info/SOURCES.txt
sphinxcontrib_osexample.egg-info/dependency_links.txt
sphinxcontrib_osexample.egg-info/namespace_packages.txt
sphinxcontrib_osexample.egg-info/not-zip-safe
sphinxcontrib_osexample.egg-info/requires.txt
sphinxcontrib_osexample.egg-info/top_level.txt