Metadata-Version: 1.1
Name: sphinxcontrib-osexample
Version: 0.1.1
Summary: Sphinx extension for OS code-blocks
Home-page: https://github.com/svx/sphinxcontrib-osexample
Author: Sven Strack
Author-email: sven@so36.net
License: BSD
Download-URL: http://pypi.python.org/pypi/sphinxcontrib-osexample
Keywords: Sphinx extension
Platform: any
Classifier: Development Status :: 4 - Beta
Classifier: Environment :: Console
Classifier: Environment :: Web Environment
Classifier: Intended Audience :: Developers
Classifier: License :: OSI Approved :: BSD License
Classifier: Operating System :: OS Independent
Classifier: Programming Language :: Python :: 2.7
Classifier: Topic :: Documentation
Classifier: Topic :: Utilities
